setup.py
dez_probability/Binomialdistribution.py
dez_probability/Gaussiandistribution.py
dez_probability/Generaldistribution.py
dez_probability/__init__.py
dez_probability.egg-info/PKG-INFO
dez_probability.egg-info/SOURCES.txt
dez_probability.egg-info/dependency_links.txt
dez_probability.egg-info/not-zip-safe
dez_probability.egg-info/top_level.txt