Metadata-Version: 1.0
Name: dez-probability
Version: 0.1
Summary: Gaussian and Binomial distributions
Home-page: UNKNOWN
Author: Jacob Sherwood
Author-email: UNKNOWN
License: UNKNOWN
Platform: UNKNOWN
